multiprocca/README.MD
multiprocca/__init__.py
multiprocca/proclauncher.py
multiprocca/requirements.txt
multiprocca/thirdparty.json
multiprocca-0.10.dist-info/LICENSE.rst
multiprocca-0.10.dist-info/METADATA
multiprocca-0.10.dist-info/WHEEL
multiprocca-0.10.dist-info/top_level.txt
multiprocca-0.10.dist-info/RECORD
