Metadata-Version: 2.1
Name: multiprocca
Version: 0.10
Summary: Enables multiprocessing with caching, eliminating the need for __main__, and ensuring unique results without duplicates
Home-page: https://github.com/hansalemaos/multiprocca
Author: Johannes Fischer
Author-email: aulasparticularesdealemaosp@gmail.com
License: MIT
Keywords: multiprocessing,cpus
Classifier: Development Status :: 4 - Beta
Classifier: Programming Language :: Python :: 3 :: Only
Classifier: Programming Language :: Python :: 3.10
Classifier: Topic :: Software Development :: Libraries :: Python Modules
Classifier: Topic :: Utilities
License-File: LICENSE.rst
Requires-Dist: dill
